README.md
setup.py
zimpute/__init__.py
zimpute/zsh.py
zimpute.egg-info/PKG-INFO
zimpute.egg-info/SOURCES.txt
zimpute.egg-info/dependency_links.txt
zimpute.egg-info/entry_points.txt
zimpute.egg-info/requires.txt
zimpute.egg-info/top_level.txt