Metadata-Version: 1.0
Name: zimpute
Version: 1.7
Summary: A low rank complement method based on scRNA-seq data
Home-page: https://github.com/zhousihan0126
Author: zhousihan0126
Author-email: zhousihan0126@gmail.com
License: MIT
Keywords: zimpute
Platform: any
